{"card_name": "Civic Gardener", "color": "G", "rarity": "common", "type": "Creature \u2013 Human Citizen", "number": 135, "color_identity": "G", "cost": "{1}{G}", "rules_text": "Whenever Civic Gardener attacks, untap target creature or land.", "flavor_text": "[i]\u201cThe man-eating flytrap breed can be more tempestuous than other breeds, so its important to clean their teeth and feelers daily.\u201d[/i]", "pt": "2/2", "special_text": "", "shape": "normal", "set": "MOX", "loyalty": "", "artist": "Aleksander Karcz", "notes": "https://www.artstation.com/artwork/XnaVPY", "image_type": "png"}