{"card_name": "Scheming Confidants", "color": "B", "rarity": "uncommon", "type": "Creature \u2013 Human Advisor", "number": 9, "color_identity": "B", "cost": "{3}{B}", "rules_text": "At the beginning of your end step, choose up to X, where X is the number of creatures that died this turn. [i](You can't choose the same mode more than once.)[/i]\n\u2022 You draw a card and you lose 1 life.\n\u2022 Each opponent discards a card.\n\u2022 Create a Treasure token.", "flavor_text": "[i][/i]", "pt": "2/2", "special_text": "", "shape": "normal", "set": "GS2", "loyalty": "", "artist": "Raul Maldonado", "notes": "https://www.pinterest.com/pin/848787861039522289/", "image_type": "png"}