{"card_name": "Flourishing Reef", "color": "G", "rarity": "common", "type": "Enchantment \u2013 Aura", "number": 181, "color_identity": "G", "cost": "{G}", "rules_text": "Enchant land\nWhen this Aura enters the battlefield, create a 1/1 blue Fish creature token.\nEnchanted land has \u201c{T}: Add one mana of any color.\u201d", "flavor_text": "[i][/i]", "pt": "", "special_text": "", "shape": "normal", "set": "KRK", "loyalty": "", "artist": "Claire Lin", "notes": "https://www.artstation.com/artwork/wJnNQ6", "image_type": "png"}