{"card_name": "Tidal Visionary", "color": "U", "rarity": "common", "type": "Creature \u2013 Merfolk Wizard", "number": 77, "color_identity": "U", "cost": "{1}{U}", "rules_text": "When this creature enters, draw a card.", "flavor_text": "[i]\u201cThe titan's slumber yields only a fragile and fraying peace. The whispers of the deep grow louder, and soon the land shall remember what it means to truly fear the might of the sea.\u201d[/i]", "pt": "1/1", "special_text": "", "shape": "normal", "set": "KRK", "loyalty": "", "artist": "Conor Burke", "notes": "https://www.artstation.com/artwork/xJGNAW", "image_type": "png"}