{"card_name": "Red Ghost", "color": "G", "rarity": "cube", "type": "Legendary Creature \u2013 Human Rogue", "number": 222, "color_identity": "G", "cost": "{4}{G}{G}", "rules_text": "When Red Ghost enters, create three 2/2 green Ape creature tokens.\nWhenever a creature you control becomes blocked or becomes the target of a spell or ability, you may have that creature phase out. [i](Treat it and anything attached to it as though they don't exist until its controller's next turn.)[/i]", "flavor_text": "[i][/i]", "pt": "3/3", "special_text": "", "shape": "normal", "set": "MRV", "loyalty": "", "artist": "Brendan Tobin", "notes": "!canoncard Grave Titan", "image_type": "png"}