{"card_name": "Staff of One", "color": "", "rarity": "common", "type": "Legendary Artifact", "number": 301, "color_identity": "C", "cost": "{3}", "rules_text": "Staff of One enters tapped unless you've lost life this turn.\n{T}, Pay X life: Search your library for an instant or sorcery card with mana value X or less and exile it, then shuffle. Until end of turn, you may cast that spell without paying its mana cost.", "flavor_text": "[i][/i]", "pt": "", "special_text": "", "shape": "normal", "set": "MRV", "loyalty": "", "artist": "Joe Quinones", "notes": "!canoncard Planar Portal", "image_type": "png"}