{"card_name": "Svartalfheim", "color": "", "rarity": "common", "type": "Legendary Land \u2013 Swamp Forest", "number": 352, "color_identity": "BG", "cost": "", "rules_text": "[i]({T}: Add {B} or {G}.)[/i]\nWhenever Svartalfheim becomes tapped, if you control fewer than two basic lands, you lose 1 life.", "flavor_text": "[i]\u201cDark Elves only follow the leaders we fear. And Svartalfheim fears no one more than me.\u201d\n\u2014Malekith the Accursed[/i]", "pt": "", "special_text": "", "shape": "normal", "set": "MRV", "loyalty": "", "artist": "Luke Ross", "notes": "!plagueland\n\n!canoncard Overgrown Tomb", "image_type": "png"}