{"card_name": "Valkyrie", "color": "W", "rarity": "common", "type": "Legendary Creature \u2013 God Warrior", "number": 49, "color_identity": "W", "cost": "{2}{W}", "rules_text": "Flying\nWhenever Valkyrie attacks, you may put a creature card with mana value 2 or less from your hand or graveyard to the battlefield tapped and attacking.", "flavor_text": "[i]\u201cDragonfang strikes swiftly and deep. You might be wise to surrender.\u201d[/i]", "pt": "2/2", "special_text": "", "shape": "normal", "set": "MRV", "loyalty": "", "artist": "Russel Dauterman", "notes": "!canoncard Bishop of Rebirth", "image_type": "png"}