{"card_name": "Vision", "color": "U", "rarity": "common", "type": "Legendary Artifact Creature \u2013 Warrior", "number": 95, "color_identity": "U", "cost": "{3}{U}{U}", "rules_text": "Flash\nFlying\nWhenever you cast a spell, you may have target creature phase out. [i](Treat it and anything attached to it as though they don't exist until its controller's next turn.)[/i]", "flavor_text": "[i][/i]", "pt": "5/5", "special_text": "", "shape": "normal", "set": "MRV", "loyalty": "", "artist": "Brandon Peterson", "notes": "!canoncard Hullbreaker Horror", "image_type": "png"}